djangomixin/__init__.py
djangomixin/class_mixin.py
djangomixin/date_mixin.py
djangomixin/mail_mixin.py
djangomixin/mixin.py
djangomixin/permission_mixin.py
djangomixin-1.0.0.dist-info/LICENSE
djangomixin-1.0.0.dist-info/METADATA
djangomixin-1.0.0.dist-info/WHEEL
djangomixin-1.0.0.dist-info/top_level.txt
djangomixin-1.0.0.dist-info/RECORD
