Metadata-Version: 2.1
Name: djangomixin
Version: 1.0.0
Summary: djangomixin is set of mixins and snippets that can help you to utilize your django functionality.
Home-page: https://github.com/njnafir/djangomixin
Author: Nj Nafir
Author-email: njnafir@gmail.com
License: MIT
Platform: UNKNOWN
Classifier: License :: OSI Approved :: MIT License
Classifier: Programming Language :: Python :: 3
Classifier: Programming Language :: Python :: 3.9
License-File: LICENSE
